contextmanaged_objects/__init__.py
contextmanaged_objects-1.0.0.dist-info/LICENSE
contextmanaged_objects-1.0.0.dist-info/METADATA
contextmanaged_objects-1.0.0.dist-info/WHEEL
contextmanaged_objects-1.0.0.dist-info/RECORD
