Metadata-Version: 2.1
Name: contextmanaged-objects
Version: 1.0.0
Summary: 
Author: Jacob Valdez
Author-email: jacobfv123@gmail.com
Requires-Python: >=3.10,<4.0
Classifier: Programming Language :: Python :: 3
Classifier: Programming Language :: Python :: 3.10
Classifier: Programming Language :: Python :: 3.11
Requires-Dist: contextmanaged-assign (>=0.1.0,<0.2.0)
Requires-Dist: inspect-mate-pp (>=0.0.4,<0.0.5)
Requires-Dist: stringcase (>=1.2.0,<2.0.0)
